setup.py
django_extra/__init__.py
django_extra.egg-info/PKG-INFO
django_extra.egg-info/SOURCES.txt
django_extra.egg-info/dependency_links.txt
django_extra.egg-info/requires.txt
django_extra.egg-info/top_level.txt
django_extra/db/__init__.py
django_extra/db/backends/__init__.py
django_extra/db/backends/mysql_tunnel/__init__.py
django_extra/db/backends/mysql_tunnel/base.py