Metadata-Version: 1.0
Name: django-extra
Version: 0.1
Summary: an extenstions of django
Home-page: UNKNOWN
Author: DrWrong
Author-email: yuhangchaney@gmail.com
License: UNKNOWN
Platform: UNKNOWN
